{
  "cycle_id": "C1615",
  "attack_multiplier": 0.89,
  "conversion_multiplier": 1e+91,
  "coexistence_rate": 0.95,
  "results": [
    {
      "seed": 30281,
      "finals": {
        "L0": 300.0,
        "L1": 30.0,
        "L2": 10.0,
        "L3": 5.0,
        "L4": 3.0,
        "L5": 2.0,
        "L6": 2.0
      },
      "coexist": true
    },
    {
      "seed": 30282,
      "finals": {
        "L0": 300.0,
        "L1": 30.0,
        "L2": 10.0,
        "L3": 5.0,
        "L4": 3.0,
        "L5": 2.0,
        "L6": 2.0
      },
      "coexist": true
    },
    {
      "seed": 30283,
      "finals": {
        "L0": 300.0,
        "L1": 30.0,
        "L2": 10.0,
        "L3": 5.0,
        "L4": 3.0,
        "L5": 2.0,
        "L6": 2.0
      },
      "coexist": true
    },
    {
      "seed": 30284,
      "finals": {
        "L0": 300.0,
        "L1": 30.0,
        "L2": 10.0,
        "L3": 5.0,
        "L4": 3.0,
        "L5": 2.0,
        "L6": 2.0
      },
      "coexist": true
    },
    {
      "seed": 30285,
      "finals": {
        "L0": 300.0,
        "L1": 30.0,
        "L2": 10.0,
        "L3": 5.0,
        "L4": 3.0,
        "L5": 2.0,
        "L6": 2.0
      },
      "coexist": true
    },
    {
      "seed": 30286,
      "finals": {
        "L0": 300.0,
        "L1": 30.0,
        "L2": 10.0,
        "L3": 5.0,
        "L4": 3.0,
        "L5": 2.0,
        "L6": 2.0
      },
      "coexist": true
    },
    {
      "seed": 30287,
      "finals": {
        "L0": 200.0,
        "L1": 0.0,
        "L2": 0.0,
        "L3": 0.0,
        "L4": 0.0,
        "L5": 0.0,
        "L6": 0.0
      },
      "coexist": false
    },
    {
      "seed": 30288,
      "finals": {
        "L0": 300.0,
        "L1": 30.0,
        "L2": 10.0,
        "L3": 5.0,
        "L4": 3.0,
        "L5": 2.0,
        "L6": 2.0
      },
      "coexist": true
    },
    {
      "seed": 30289,
      "finals": {
        "L0": 300.0,
        "L1": 30.0,
        "L2": 10.0,
        "L3": 5.0,
        "L4": 3.0,
        "L5": 2.0,
        "L6": 2.0
      },
      "coexist": true
    },
    {
      "seed": 30290,
      "finals": {
        "L0": 300.0,
        "L1": 30.0,
        "L2": 10.0,
        "L3": 5.0,
        "L4": 3.0,
        "L5": 2.0,
        "L6": 2.0
      },
      "coexist": true
    },
    {
      "seed": 30291,
      "finals": {
        "L0": 300.0,
        "L1": 30.0,
        "L2": 10.0,
        "L3": 5.0,
        "L4": 3.0,
        "L5": 2.0,
        "L6": 2.0
      },
      "coexist": true
    },
    {
      "seed": 30292,
      "finals": {
        "L0": 300.0,
        "L1": 30.0,
        "L2": 10.0,
        "L3": 5.0,
        "L4": 3.0,
        "L5": 2.0,
        "L6": 2.0
      },
      "coexist": true
    },
    {
      "seed": 30293,
      "finals": {
        "L0": 300.0,
        "L1": 30.0,
        "L2": 10.0,
        "L3": 5.0,
        "L4": 3.0,
        "L5": 2.0,
        "L6": 2.0
      },
      "coexist": true
    },
    {
      "seed": 30294,
      "finals": {
        "L0": 300.0,
        "L1": 30.0,
        "L2": 10.0,
        "L3": 5.0,
        "L4": 3.0,
        "L5": 2.0,
        "L6": 2.0
      },
      "coexist": true
    },
    {
      "seed": 30295,
      "finals": {
        "L0": 300.0,
        "L1": 30.0,
        "L2": 10.0,
        "L3": 5.0,
        "L4": 3.0,
        "L5": 2.0,
        "L6": 2.0
      },
      "coexist": true
    },
    {
      "seed": 30296,
      "finals": {
        "L0": 300.0,
        "L1": 30.0,
        "L2": 10.0,
        "L3": 5.0,
        "L4": 3.0,
        "L5": 2.0,
        "L6": 2.0
      },
      "coexist": true
    },
    {
      "seed": 30297,
      "finals": {
        "L0": 300.0,
        "L1": 30.0,
        "L2": 10.0,
        "L3": 5.0,
        "L4": 3.0,
        "L5": 2.0,
        "L6": 2.0
      },
      "coexist": true
    },
    {
      "seed": 30298,
      "finals": {
        "L0": 300.0,
        "L1": 30.0,
        "L2": 10.0,
        "L3": 5.0,
        "L4": 3.0,
        "L5": 2.0,
        "L6": 2.0
      },
      "coexist": true
    },
    {
      "seed": 30299,
      "finals": {
        "L0": 300.0,
        "L1": 30.0,
        "L2": 10.0,
        "L3": 5.0,
        "L4": 3.0,
        "L5": 2.0,
        "L6": 2.0
      },
      "coexist": true
    },
    {
      "seed": 30300,
      "finals": {
        "L0": 300.0,
        "L1": 30.0,
        "L2": 10.0,
        "L3": 5.0,
        "L4": 3.0,
        "L5": 2.0,
        "L6": 2.0
      },
      "coexist": true
    }
  ]
}